Workbook
Name Aporte: 'Controle de Investimentos'!$D$17
Name Patrimonio: 'Controle de Investimentos'!$D$20
Name Qtd_Anos: 'Controle de Investimentos'!$D$18
Name Rendimento_Carteira: 'Controle de Investimentos'!$D$13
Name Salario: 'Controle de Investimentos'!$D$12
Name Sugestao_Investimento: 'Controle de Investimentos'!$D$14
Name Taxa_Mensal: 'Controle de Investimentos'!$D$19

Sheet Controle de Investimentos
B11: CONFIGURAÇÕES
B12: Salário | D12: 2000
B13: Rendimento carteira | D13: 0.006
B14: Sugestão de Rendimento | D14: =D12*30% -> 600
B16: IVESTIMENTO MENSAL
B17: Quanto investir por mês? | D17: 200
B18: Por quantos anos? | D18: 5
B19: Taxa de rendimento mensal? | D19: 0.01079
B20: Patrimônio acumulado? | D20: =FV(Taxa_Mensal,Qtd_Anos*12,Aporte*-1) -> 16755.383
B21: Dividendos mensais? | D21: =Patrimonio*Rendimento_Carteira -> 100.5323
B23: Cenários | D23: Dividendo
A24: 2 | B24: Quanto em 2 anos? | C24: =FV($D$19,$A24*12,$D$17*-1) -> 5445.5255 | D24: =C24*Rendimento_Carteira -> 32.673153
A25: 5 | B25: Quanto em 5 anos? | C25: =FV($D$19,$A25*12,$D$17*-1) -> 16755.383 | D25: =C25*Rendimento_Carteira -> 100.5323
A26: 10 | B26: Quanto em 10 anos? | C26: =FV($D$19,$A26*12,$D$17*-1) -> 48656.843 | D26: =C26*Rendimento_Carteira -> 291.94106
A27: 20 | B27: Quanto em 20 anos? | C27: =FV($D$19,$A27*12,$D$17*-1) -> 225039.68 | D27: =C27*Rendimento_Carteira -> 1350.2381
A28: 30 | B28: Quanto em 30 anos? | C28: =FV($D$19,$A28*12,$D$17*-1) -> 864433.93 | D28: =C28*Rendimento_Carteira -> 5186.6036
B31: PERFIL | C31: Moderado
B32: VALOR A SER INVESTIDO POR MÊS | C32: =Aporte -> 200
B34: TIPO DE FI | C34: Percentual Sugerido | D34: Valores
B35: PAPEL | C35: =VLOOKUP($C$31&"-"&B35,'Tabela de Apoio'!$A:$D,4,0) -> 0.32 | D35: =C35*$C$32 -> 64
B36: TIJOLO | C36: =VLOOKUP($C$31&"-"&B36,'Tabela de Apoio'!$A:$D,4,0) -> 0.35 | D36: =C36*$C$32 -> 70
B37: HÍBRIDOS | C37: =VLOOKUP($C$31&"-"&B37,'Tabela de Apoio'!$A:$D,4,0) -> 0.08 | D37: =C37*$C$32 -> 16
B38: FOFs | C38: =VLOOKUP($C$31&"-"&B38,'Tabela de Apoio'!$A:$D,4,0) -> 0.05 | D38: =C38*$C$32 -> 10
B39: DESENVOLVIMENTO | C39: =VLOOKUP($C$31&"-"&B39,'Tabela de Apoio'!$A:$D,4,0) -> 0.1 | D39: =C39*$C$32 -> 20
B40: HOTELÁRIAS | C40: =VLOOKUP($C$31&"-"&B40,'Tabela de Apoio'!$A:$D,4,0) -> 0.1 | D40: =C40*$C$32 -> 20
D41: =SUM(D35:D40) -> 200

Sheet Tabela de Apoio
A2: CHAVE | B2: PERFIL | C2: TIPO DE FI | D2: % | H2: %
A3: =B3&"-"&C3 -> Conservador-PAPEL | B3: Conservador | C3: PAPEL | D3: 0.3 | G3: Moderado-TIJOLO | H3: =VLOOKUP(G3,$A:$D,4,0) -> 0.35
A4: =B4&"-"&C4 -> Conservador-TIJOLO | B4: Conservador | C4: TIJOLO | D4: 0.5
A5: =B5&"-"&C5 -> Conservador-HÍBRIDOS | B5: Conservador | C5: HÍBRIDOS | D5: 0.1
A6: =B6&"-"&C6 -> Conservador-FOFs | B6: Conservador | C6: FOFs | D6: 0.1
A7: =B7&"-"&C7 -> Conservador-DESENVOLVIMENTO | B7: Conservador | C7: DESENVOLVIMENTO | D7: 0
A8: =B8&"-"&C8 -> Conservador-HOTELÁRIAS | B8: Conservador | C8: HOTELÁRIAS | D8: 0
A9: =B9&"-"&C9 -> Moderado-PAPEL | B9: Moderado | C9: PAPEL | D9: 0.32
A10: =B10&"-"&C10 -> Moderado-TIJOLO | B10: Moderado | C10: TIJOLO | D10: 0.35
A11: =B11&"-"&C11 -> Moderado-HÍBRIDOS | B11: Moderado | C11: HÍBRIDOS | D11: 0.08
A12: =B12&"-"&C12 -> Moderado-FOFs | B12: Moderado | C12: FOFs | D12: 0.05
A13: =B13&"-"&C13 -> Moderado-DESENVOLVIMENTO | B13: Moderado | C13: DESENVOLVIMENTO | D13: 0.1
A14: =B14&"-"&C14 -> Moderado-HOTELÁRIAS | B14: Moderado | C14: HOTELÁRIAS | D14: 0.1
A15: =B15&"-"&C15 -> Agressivo-PAPEL | B15: Agressivo | C15: PAPEL | D15: 0.5
... A20: =B20&"-"&C20 -> Agressivo-HOTELÁRIAS | B20: Agressivo | C20: HOTELÁRIAS | D20: 0.1
